specsy/__init__.py
specsy/config.toml
specsy/core.py
specsy/io.py
specsy/tools.py
specsy/treatement.py
specsy/inference/__init__.py
specsy/inference/emission.py
specsy/innate/__init__.py
specsy/innate/interpol_pytensor.py
specsy/innate/main.py
specsy/models/__init__.py
specsy/models/chemistry.py
specsy/models/chemistry_inference.py
specsy/models/emissivity.py
specsy/models/extinction.py
specsy/models/fluxes_line.py
specsy/models/nebular_continuum.py
specsy/operations/__init__.py
specsy/operations/interpolation.py
specsy/operations/pytensors.py
specsy/operations/tensors.py
specsy/operations/tests.py
specsy/plotting/__init__.py
specsy/plotting/bokeh_functions.py
specsy/plotting/plots.py
specsy/plotting/specsy_theme.toml
specsy/workflow/__init__.py
specsy-0.6.5.dist-info/METADATA
specsy-0.6.5.dist-info/WHEEL
specsy-0.6.5.dist-info/top_level.txt
specsy-0.6.5.dist-info/RECORD
