Metadata-Version: 2.4
Name: specsy
Version: 0.6.5
Summary: Model fitting package for the chemical analysis of astronomical spectra
Author-email: Vital Fernández <vgf@umich.edu>
License-Expression: GPL-3.0-or-later
Classifier: Programming Language :: Python :: 3
Classifier: Programming Language :: Python :: 3.11
Requires-Python: >=3.11
Requires-Dist: arviz~=0.21
Requires-Dist: corner~=2.2
Requires-Dist: h5netcdf~=1.3.0
Requires-Dist: jax~=0.4
Requires-Dist: jaxlib~=0.4
Requires-Dist: lime-stable~=2.0.dev13
Requires-Dist: lmfit~=1.3
Requires-Dist: bokeh~=3.8
Requires-Dist: matplotlib~=3.10
Requires-Dist: numpy~=2.3
Requires-Dist: pymc~=5.1
Requires-Dist: scipy~=1.16
Requires-Dist: toml~=0.10
Requires-Dist: tomli>=2.0.0; python_version < "3.11"
Requires-Dist: xarray~=2024.3.0
Provides-Extra: tensors
Requires-Dist: pytensor~=2.20; extra == "tensors"
Provides-Extra: docs
Requires-Dist: sphinx-rtd-theme~=3.0; extra == "docs"
Requires-Dist: ipympl~=0.9; extra == "docs"
Requires-Dist: myst-nb~=1.3; extra == "docs"
Provides-Extra: tests
Requires-Dist: pytest~=8.4; extra == "tests"
Requires-Dist: pytest-cov~=7.0; extra == "tests"
Requires-Dist: pytest-mpl~=0.17; extra == "tests"
